vainu/dateutil/__init__.py
vainu_dateutil-2020.12.0.dist-info/METADATA
vainu_dateutil-2020.12.0.dist-info/WHEEL
vainu_dateutil-2020.12.0.dist-info/top_level.txt
vainu_dateutil-2020.12.0.dist-info/RECORD
