Metadata-Version: 2.1
Name: vainu-dateutil
Version: 2020.12.0
Summary: Vainu specific date-related utilities.
Home-page: https://vainu.io/
Author: Vainu Finland Oy
Author-email: kimmo@vainu.io
License: Proprietary
Platform: UNKNOWN
Requires-Dist: python-dateutil
